{
  "_generic": {
    "defaultPackage": "main",
    "invalidationHash": "8968e085a9b01fea87464bb2aafac2dc188919960c897620eb9424c4c737327c",
    "location": "",
    "packages": {
      "main": "3.11.0"
    },
    "sourcesAggregatedHash": null,
    "subsystem": "python"
  },
  "_subsystem": {
    "application": false,
    "pythonAttr": "python310",
    "sourceFormats": {
      "PyYAML": "wheel"
    }
  },
  "sources": {
    "PyYAML": {
      "6.0": {
        "hash": "sha256-+E+8mLAZ/vLumhyzzpPjGHpt8LJTimUb+4kCVLqfkLU=",
        "type": "http",
        "url": "https://files.pythonhosted.org/packages/cp310/P/PyYAML/PyYAML-6.0-cp310-cp310-manylinux_2_5_x86_64.manylinux1_x86_64.manylinux_2_12_x86_64.manylinux2010_x86_64.whl"
      }
    }
  }
}
